LICENSE
README.md
setup.py
env_test_package/__init__.py
env_test_package/hello.py
env_test_package.egg-info/PKG-INFO
env_test_package.egg-info/SOURCES.txt
env_test_package.egg-info/dependency_links.txt
env_test_package.egg-info/top_level.txt